llm_llama_server.py
llm_llama_server-0.2.dist-info/METADATA
llm_llama_server-0.2.dist-info/WHEEL
llm_llama_server-0.2.dist-info/entry_points.txt
llm_llama_server-0.2.dist-info/top_level.txt
llm_llama_server-0.2.dist-info/RECORD
