Metadata-Version: 2.4
Name: llm-llama-server
Version: 0.2
Summary: Interact with llama-server models
Author: Simon Willison
License-Expression: Apache-2.0
Project-URL: Homepage, https://github.com/simonw/llm-llama-server
Project-URL: Changelog, https://github.com/simonw/llm-llama-server/releases
Project-URL: Issues, https://github.com/simonw/llm-llama-server/issues
Project-URL: CI, https://github.com/simonw/llm-llama-server/actions
Requires-Python: >=3.9
Requires-Dist: llm>=0.26
Provides-Extra: test
Requires-Dist: pytest; extra == "test"
